Metadata-Version: 1.0
Name: emaillib1
Version: 1.0.0
Summary: adds commas to big numbers
Home-page: UNKNOWN
Author: UNKNOWN
Author-email: willhpayne@icloud.com
License: UNKNOWN
Platform: UNKNOWN
